docthing/__init__.py
docthing/__main__.py
docthing/config.py
docthing/constants.py
docthing/documentation_blob.py
docthing/documentation_content.py
docthing/extractor.py
docthing/tree.py
docthing/util.py
docthing/plugins/__init__.py
docthing/plugins/exporter_interface.py
docthing/plugins/manager.py
docthing/plugins/meta_interpreter_interface.py
docthing/plugins/plugin_interface.py
docthing/plugins/exporter/__init__.py
docthing/plugins/exporter/markdown.py
docthing/plugins/meta_interpreter/__init__.py
docthing/plugins/meta_interpreter/nav.py
docthing/plugins/meta_interpreter/plantuml.py
docthing-0.0.9.dist-info/METADATA
docthing-0.0.9.dist-info/WHEEL
docthing-0.0.9.dist-info/entry_points.txt
docthing-0.0.9.dist-info/licenses/LICENSE
docthing-0.0.9.dist-info/RECORD
