Metadata-Version: 2.3
Name: docthing
Version: 0.0.9
Summary: Simple tool to extract high-level documentation from the projects source code
Project-URL: Homepage, https://github.com/ferdiu/docthing
Project-URL: Issues, https://github.com/ferdiu/docthing/issues
Author-email: Federico Manzella <ferdiu.cow.a.bunga@gmail.com>
Classifier: License :: OSI Approved :: MIT License
Classifier: Operating System :: OS Independent
Classifier: Programming Language :: Python :: 3
Classifier: Topic :: Documentation
Classifier: Topic :: Software Development
Classifier: Topic :: Software Development :: Documentation
Requires-Python: >=3.8
Requires-Dist: pyjson5
Requires-Dist: schema
Provides-Extra: dev
Requires-Dist: autopep8; extra == 'dev'
Provides-Extra: test
Requires-Dist: flake8; extra == 'test'
Requires-Dist: pytest; extra == 'test'
Requires-Dist: pytest-cov; extra == 'test'
